odoo/addons/intrastat_product_generic/README.rst
odoo/addons/intrastat_product_generic/__init__.py
odoo/addons/intrastat_product_generic/__manifest__.py
odoo/addons/intrastat_product_generic/i18n/es.po
odoo/addons/intrastat_product_generic/i18n/intrastat_product_generic.pot
odoo/addons/intrastat_product_generic/i18n/it.po
odoo/addons/intrastat_product_generic/readme/CONTRIBUTORS.md
odoo/addons/intrastat_product_generic/readme/DESCRIPTION.md
odoo/addons/intrastat_product_generic/security/intrastat_security.xml
odoo/addons/intrastat_product_generic/static/description/icon.png
odoo/addons/intrastat_product_generic/static/description/index.html
odoo/addons/intrastat_product_generic/views/intrastat_product.xml
odoo_addon_intrastat_product_generic-17.0.1.0.0.2.dist-info/METADATA
odoo_addon_intrastat_product_generic-17.0.1.0.0.2.dist-info/WHEEL
odoo_addon_intrastat_product_generic-17.0.1.0.0.2.dist-info/top_level.txt
odoo_addon_intrastat_product_generic-17.0.1.0.0.2.dist-info/RECORD
