Metadata-Version: 2.1
Name: odoo-addon-intrastat_product_generic
Version: 17.0.1.0.0.2
Requires-Python: >=3.10
Requires-Dist: odoo-addon-intrastat_product>=17.0dev,<17.1dev
Requires-Dist: odoo>=17.0a,<17.1dev
Summary: Generic Intrastat Product Declaration
Home-page: https://github.com/OCA/intrastat-extrastat
License: AGPL-3
Author: Noviat,Odoo Community Association (OCA)
Author-email: support@odoo-community.org
Classifier: Programming Language :: Python
Classifier: Framework :: Odoo
Classifier: Framework :: Odoo :: 17.0
Classifier: License :: OSI Approved :: GNU Affero General Public License v3
